pyezzi/__init__.py
pyezzi/__main__.py
pyezzi/cli.py
pyezzi/common.c
pyezzi/common.cpython-314-darwin.so
pyezzi/common.pxd
pyezzi/common.pyx
pyezzi/flatten.c
pyezzi/flatten.cpython-314-darwin.so
pyezzi/flatten.pyx
pyezzi/grad.c
pyezzi/grad.cpython-314-darwin.so
pyezzi/grad.pyx
pyezzi/laplace.c
pyezzi/laplace.cpython-314-darwin.so
pyezzi/laplace.pyx
pyezzi/misc.py
pyezzi/py.typed
pyezzi/thickness.py
pyezzi/yezzi.c
pyezzi/yezzi.cpython-314-darwin.so
pyezzi/yezzi.pyx
pyezzi-0.8.3.dist-info/licenses/LICENSE
pyezzi-0.8.3.dist-info/METADATA
pyezzi-0.8.3.dist-info/WHEEL
pyezzi-0.8.3.dist-info/entry_points.txt
pyezzi-0.8.3.dist-info/top_level.txt
pyezzi-0.8.3.dist-info/RECORD
