Metadata-Version: 2.4
Name: pyezzi
Version: 0.8.3
Author-email: Nicolas Cedilnik <nicoco@nicoco.fr>
License-Expression: CECILL-C
Keywords: medical image processing
Classifier: Development Status :: 4 - Beta
Classifier: Intended Audience :: Developers
Classifier: Intended Audience :: Education
Classifier: Intended Audience :: Science/Research
Requires-Python: >=3.10
License-File: LICENSE
Requires-Dist: numpy>=2
Provides-Extra: cli
Requires-Dist: scipy>=1.13.1; extra == "cli"
Requires-Dist: simpleitk>=2.4.1; extra == "cli"
Provides-Extra: example
Requires-Dist: ipykernel>=6.29.5; extra == "example"
Requires-Dist: matplotlib>=3.9.4; extra == "example"
Dynamic: license-file
